LICENSE
MANIFEST.in
README.md
requirements.txt
setup.cfg
setup.py
icq_bot/__init__.py
icq_bot/bot.py
icq_bot/constant.py
icq_bot/dispatcher.py
icq_bot/event.py
icq_bot/filter.py
icq_bot/handler.py
icq_bot/myteam.py
icq_bot/types.py
icq_bot/util.py
mailru_im_bot_updated.egg-info/PKG-INFO
mailru_im_bot_updated.egg-info/SOURCES.txt
mailru_im_bot_updated.egg-info/dependency_links.txt
mailru_im_bot_updated.egg-info/not-zip-safe
mailru_im_bot_updated.egg-info/requires.txt
mailru_im_bot_updated.egg-info/top_level.txt