Metadata-Version: 2.1
Name: mailru-im-bot-updated
Version: 0.0.25
Summary: Pure Python interface for Bot API. Bot cookbook for Humans.
Home-page: https://github.com/Lunatik-cyber/bot-python-icq
Author: ICQ LLC (Mail.Ru Group)
Author-email: support@icq.com
License: MIT
Keywords: mailru im icq_bot api
Classifier: Intended Audience :: Developers
Classifier: Topic :: Software Development :: Libraries :: Python Modules
Classifier: Topic :: Communications :: Chat
Classifier: Topic :: Internet
Classifier: Programming Language :: Python :: 2
Classifier: Programming Language :: Python :: 2.7
Classifier: Programming Language :: Python :: 3
Classifier: Programming Language :: Python :: 3.4
Classifier: Programming Language :: Python :: 3.5
Classifier: Programming Language :: Python :: 3.6
Classifier: Programming Language :: Python :: 3.7
Classifier: Programming Language :: Python :: 3.8
Classifier: Programming Language :: Python :: 3.9
Classifier: Programming Language :: Python :: 3.10
Classifier: Operating System :: OS Independent
Requires-Python: >= 2.7, != 3.0.*, != 3.1.*, != 3.2.*, != 3.3.*
License-File: LICENSE
